sstc_io/__init__.py
sstc_io/sftp.py
sstc_io/version.py
sstc_io/yaml_io.py
sstc_io-0.1.1.dist-info/METADATA
sstc_io-0.1.1.dist-info/WHEEL
sstc_io-0.1.1.dist-info/RECORD
